origamipy/__init__.py
origamipy/_version.py
origamipy/biases.py
origamipy/conditions.py
origamipy/config_process.py
origamipy/datatypes.py
origamipy/decorrelate.py
origamipy/files.py
origamipy/mbar_wrapper.py
origamipy/nearest_neighbour.py
origamipy/outputs.py
origamipy/plotting.py
origamipy/remc.py
origamipy/us_process.py
origamipy/utility.py
origamipy-1.1.2.dist-info/LICENSE.txt
origamipy-1.1.2.dist-info/METADATA
origamipy-1.1.2.dist-info/WHEEL
origamipy-1.1.2.dist-info/top_level.txt
origamipy-1.1.2.dist-info/RECORD
