Metadata-Version: 2.1
Name: origamipy
Version: 1.1.2
Summary: Python package for analysis, visualization, and support for the LatticeDNAOrigami simulation program.
Home-page: https://github.com/cumberworth/origamipy
Author: Alexander Cumberworth
Author-email: alex@cumberworth.org
Project-URL: Paper, https://doi.org/10.48550/arXiv.2204.02499
Project-URL: Data for paper, https://doi.org/10.5281/zenodo.6414264
Classifier: Programming Language :: Python :: 3
Classifier: License :: OSI Approved :: MIT License
Classifier: Operating System :: POSIX :: Linux
Requires-Python: >=3.6
License-File: LICENSE.txt
Requires-Dist: matplotlib
Requires-Dist: matplotlibstyles (==0.2.0)
Requires-Dist: numpy
Requires-Dist: pandas
Requires-Dist: pymbar
Requires-Dist: scipy
